{
  "title": "【2025年最新】Google AI全サービスでExcel分析を完全攻略 - Gemini・AI Studio・Labs実験ツール総動員の30分ハンズオン",
  "link": "https://note.com/nomuragoro/n/n085251d79907",
  "pub_date": "Thu, 19 Jun 2025 01:13:06 +0900",
  "creator": "中 翔（のむらごろう）| IT教育の効果的な受講方法の案内人",
  "guid": "https://note.com/nomuragoro/n/n085251d79907",
  "description": "\n<![CDATA[ <figure name=\"fd89e0a4-a05e-4be8-a921-ebeecb4c22a0\" id=\"fd89e0a4-a05e-4be8-a921-ebeecb4c22a0\"><img src=\"https://assets.st-note.com/production/uploads/images/196941147/picture_pc_c27a417cbe3357415c2d0c02476fe852.gif\" alt=\"\" width=\"480\" height=\"270\"><figcaption>GoogleAIサービスで作成したText2ImageをImage2Movieで動画化したもの</figcaption></figure><p name=\"23611660-358b-4095-b4b8-109462aec7d2\" id=\"23611660-358b-4095-b4b8-109462aec7d2\">（この記事は以下コンテスト用に作成したものであり、AIの効果を感じて欲しいので特記事項がないものはあえてAI生成のままにしています。タイトルも変えていません）</p><br/><a href='https://note.com/nomuragoro/n/n085251d79907'>続きをみる</a> ]]>\n",
  "post_id": null,
  "content": null,
  "post_date": null,
  "status": null,
  "source": "rss"
}