{
  "title": "国会図書館を実際に使ってみた｜普通の図書館とは全く違う施設だった",
  "link": "https://note.com/nomuragoro/n/nbfd7dadb249b",
  "pub_date": "Sun, 08 Jun 2025 20:36:09 +0900",
  "creator": "中 翔（のむらごろう）| IT教育の効果的な受講方法の案内人",
  "guid": "https://note.com/nomuragoro/n/nbfd7dadb249b",
  "description": "\n<![CDATA[ <p name=\"4269c50e-8ddf-42e9-a3d7-584e6d612b30\" id=\"4269c50e-8ddf-42e9-a3d7-584e6d612b30\">「日本最大の図書館」として有名な国会図書館。研究や調べ物で一度は利用してみたいと思い、実際に足を運んでみました。</p><p name=\"18ded850-ae77-47f6-9a63-e1ef92fe7bd7\" id=\"18ded850-ae77-47f6-9a63-e1ef92fe7bd7\"><strong>結論から言うと、一般的な図書館とは全く異なる施設</strong>でした。期待していた「気軽に本を読める場所」ではなく、「専門的な調査・研究のための資料庫」だったのです。</p><br/><a href='https://note.com/nomuragoro/n/nbfd7dadb249b'>続きをみる</a> ]]>\n",
  "post_id": null,
  "content": null,
  "post_date": null,
  "status": null,
  "source": "rss"
}