{
    "id": "n8e24dfe9c",
    "title": "Gistのソースコードをうまく貼り付けて表示をキレイにしよう！",
    "publish_date": "2020-07-20T14:17:47+09:00",
    "status": "publish",
    "post_type": "post",
    "content": [
        "# Gistの悩み",
        "ソースコードの一部を貼り付けたい場合があります。",
        "codeで書けば任意に取り出すことができますが、これをGistでやるためにはどうすればよいのか、を試行錯誤しました。",
        "Gistの話なので、相変わらずエンジニア・プログラマー向けです。",
        "ご容赦ください。",
        "# サンプルコード",
        "このページでは以下の記事のコードを使っています。",
        "https://note.com/nomuragoro/n/nc4374b8b4fc1",
        "Gistの管理をしやすくする拡張機能などの紹介もしていますので、合わせて確認してもらえると少し便利になります。",
        "## 普通に貼り付ける",
        "今回使用するコードは",
        "https://gist.github.com/shimajima-eiji/a3077686179f1c298e6cc1d4845554bf",
        "にあるのですが、これを貼り付けると全部出てきてしまいます。",
        "https://gist.github.com/shimajima-eiji/a3077686179f1c298e6cc1d4845554bf",
        "ここでほしいのは、script.jsだけです。",
        "## 取り出す",
        "そこで、https://gist.github.com/shimajima-eiji/a3077686179f1c298e6cc1d4845554bf#file-script-js のように「#file-」をつけてファイル名を指定すると、必要な部分だけが取り出せます。",
        "https://gist.github.com/shimajima-eiji/a3077686179f1c298e6cc1d4845554bf#file-script-js",
        "非常に見やすくなりました。"
    ],
    "images": [
        {
            "src": "/assets/n8e24dfe9c8bf_b5aac5f65353a41a6df288b733f28644.png",
            "alt": "",
            "width": null,
            "height": null
        }
    ]
}